tests/__init__.py
tests/test_common.py
tests/test_models.py
tests/test_question.py
tests/test_think.py
yunyun/__init__.py
yunyun/common.py
yunyun/question.py
yunyun/think.py
yunyun/thinkdata.py
yunyun-0.2.2.dist-info/LICENSE
yunyun-0.2.2.dist-info/METADATA
yunyun-0.2.2.dist-info/WHEEL
yunyun-0.2.2.dist-info/entry_points.txt
yunyun-0.2.2.dist-info/top_level.txt
yunyun-0.2.2.dist-info/RECORD
