Metadata-Version: 2.1
Name: yunyun
Version: 0.2.2
Summary: A library to help people make decisions.
Home-page: UNKNOWN
Author: Brendon Lin
Author-email: brendon.lin@outlook.com
License: UNKNOWN
Platform: UNKNOWN
Requires-Dist: tabulate (>=0.8.6)
